{
  "common": {
    "name": "parser",
    "version": "1.1.8",
    "news": {
      "1.1.8": {
        "en": "Check that a link is configured",
        "de": "Überprüfen Sie, ob ein Link konfiguriert ist",
        "ru": "Проверьте, что ссылка настроена",
        "pt": "Verifique se um link está configurado",
        "nl": "Controleer dat een link in beslag genomen is",
        "fr": "Vérifiez qu'un lien est configuré",
        "it": "Controllare che un link sia configurato",
        "es": "Compruebe que un enlace está configurado",
        "pl": "Check, że połączenie jest skonfigurowane",
        "zh-cn": "核对股"
      },
      "1.1.7": {
        "en": "Fix potential crash cases reported by Sentry",
        "de": "Behebt mögliche Crashfälle, die von Sentry gemeldet wurden",
        "ru": "Исправление потенциальных аварийных случаев, сообщенных Sentry",
        "pt": "Corrigir casos potenciais de acidente relatados pela Sentry",
        "nl": "Vertaling:",
        "fr": "Correction des cas de crash potentiels signalés par Sentry",
        "it": "Fissare potenziali casi di crash segnalati da Sentry",
        "es": "Fijar posibles casos de accidentes reportados por Sentry",
        "pl": "Fixowe przypadki katastrofy (ang.)",
        "zh-cn": "Sentry报告的潜在事故"
      },
      "1.1.6": {
        "en": "Set method to \"GET\" when requesting URLs",
        "de": "Setzen Sie die Methode auf \"GET\", wenn Sie URLs anfordern",
        "ru": "Установите метод «GET» при запросе URL-адресов",
        "pt": "Defina o método como \"GET\" ao solicitar URLs",
        "nl": "Stel methode in op \"GET\" bij het opvragen van URL's",
        "fr": "Définir la méthode sur \"GET\" lors de la demande d'URL",
        "it": "Imposta il metodo su \"GET\" quando richiedi gli URL",
        "es": "Establezca el método en \"GET\" al solicitar URL",
        "pl": "Ustaw metodę na „GET” podczas żądania adresów URL",
        "zh-cn": "请求 URL 时将方法设置为“GET”"
      },
      "1.1.5": {
        "en": "Ignore objects without configuration for parser and log it",
        "de": "Objekte ohne Konfiguration für Parser ignorieren und protokollieren",
        "ru": "Игнорировать объекты без конфигурации для парсера и логировать это",
        "pt": "Ignore objetos sem configuração para analisador e registre-os",
        "nl": "Negeer objecten zonder configuratie voor parser en log het in",
        "fr": "Ignorer les objets sans configuration pour l'analyseur et le consigner",
        "it": "Ignora gli oggetti senza configurazione per il parser e registralo",
        "es": "Ignorar objetos sin configuración para el analizador y registrarlo",
        "pl": "Ignoruj obiekty bez konfiguracji dla parsera i loguj je",
        "zh-cn": "忽略没有解析器配置的对象并记录它"
      },
      "1.1.4": {
        "en": "Fix crash case reported by Sentry",
        "de": "Absturzfall behoben, der von Sentry gemeldet wurde",
        "ru": "Исправить случай сбоя, о котором сообщил Sentry",
        "pt": "Corrigir caso de falha relatado pelo Sentinela",
        "nl": "Herstel crashgeval gemeld door Sentry",
        "fr": "Correction d'un cas de crash signalé par Sentry",
        "it": "Risolto il caso di crash segnalato da Sentry",
        "es": "Solucionar caso de bloqueo informado por Sentry",
        "pl": "Napraw przypadek awarii zgłoszony przez Sentry",
        "zh-cn": "修复 Sentry 报告的崩溃案例"
      },
      "1.1.3": {
        "en": "if regex did not match set defined replacement value (or null)",
        "de": "wenn Regex nicht übereinstimmte definierter Ersatzwert gesetzt (oder null)",
        "ru": "если регулярное выражение не соответствует заданному значению замены (или null)",
        "pt": "se regex não correspondeu ao valor de substituição definido definido (ou nulo)",
        "nl": "als regex niet overeenkomt met de ingestelde vervangingswaarde (of null)",
        "fr": "si regex ne correspond pas à la valeur de remplacement définie définie (ou nulle)",
        "it": "se regex non corrispondeva imposta il valore di sostituzione definito (o null)",
        "es": "si la expresión regular no coincide con el valor de reemplazo definido establecido (o nulo)",
        "pl": "jeśli wyrażenie regularne nie pasuje do ustawionej zdefiniowanej wartości zastępczej (lub null)",
        "zh-cn": "如果正则表达式不匹配设置定义的替换值（或 null）"
      },
      "1.1.2": {
        "en": "Fix initialization of new parser objects",
        "de": "Korrigieren Sie die Initialisierung neuer Parser-Objekte",
        "ru": "Исправить инициализацию новых объектов парсера",
        "pt": "Corrige a inicialização de novos objetos do analisador",
        "nl": "Initialisatie van nieuwe parser-objecten repareren",
        "fr": "Correction de l'initialisation des nouveaux objets d'analyseur",
        "it": "Correzione dell'inizializzazione di nuovi oggetti parser",
        "es": "Arreglar la inicialización de nuevos objetos del analizador.",
        "pl": "Napraw inicjalizację nowych obiektów parsera",
        "zh-cn": "修复新解析器对象的初始化"
      }
    },
    "title": "Parser",
    "titleLang": {
      "en": "Parser",
      "de": "Parser",
      "ru": "Синтаксический анализатор",
      "pt": "Analisador",
      "nl": "Parser",
      "fr": "Analyseur",
      "it": "Parser",
      "es": "Analizador",
      "pl": "Analizator składni",
      "zh-cn": "分析器"
    },
    "desc": {
      "en": "This adapter allows to extract values from HTTP URLs or from files",
      "de": "Dieser Adapter ermöglicht das Extrahieren von Werten aus HTTP-Seiten oder aus Dateien",
      "ru": "Этот адаптер позволяет извлекать значения из HTTP страниц или файлов",
      "pt": "Este adaptador permite extrair valores de URLs HTTP ou de arquivos",
      "nl": "Met deze adapter kunnen waarden uit HTTP-URL's of uit bestanden worden geëxtraheerd",
      "fr": "Cet adaptateur permet d'extraire des valeurs à partir d'URL HTTP ou de fichiers",
      "it": "Questo adattatore consente di estrarre valori da URL HTTP o da file",
      "es": "Este adaptador permite extraer valores de URL HTTP o de archivos",
      "pl": "Ten adapter umożliwia wyodrębnianie wartości z adresów URL HTTP lub z plików",
      "zh-cn": "这器允许提取价值从HTTP URLs或从文件"
    },
    "authors": [
      "bluefox <dogafox@gmail.com>"
    ],
    "license": "MIT",
    "platform": "Javascript/Node.js",
    "mode": "daemon",
    "loglevel": "info",
    "messagebox": true,
    "materialize": true,
    "icon": "parser.png",
    "readme": "https://github.com/ioBroker/ioBroker.parser/blob/master/README.md",
    "keywords": [
      "url",
      "html",
      "file",
      "parser"
    ],
    "dependencies": [
      {
        "js-controller": ">=2.0.0"
      }
    ],
    "globalDependencies": [
      {
        "admin": ">=3.0.0"
      }
    ],
    "extIcon": "https://raw.githubusercontent.com/ioBroker/ioBroker.parser/master/admin/parser.png",
    "type": "logic",
    "plugins": {
      "sentry": {
        "dsn": "https://24bf60e0e158444599caf102391b2f2f@sentry.iobroker.net/172"
      }
    },
    "connectionType": "none",
    "dataSource": "poll",
    "tier": 3
  },
  "native": {
    "pollInterval": "5000",
    "requestTimeout": "60000",
    "acceptInvalidCertificates": true,
    "useInsecureHTTPParser": false
  }
}
